tools/__init__.py
tools/array.py
tools/rotation.py
tools/text.py
tools/xarray.py
xmca/__init__.py
xmca/array.py
xmca/version.py
xmca/xarray.py
xmca/tools/__init__.py
xmca/tools/array.py
xmca/tools/rotation.py
xmca/tools/text.py
xmca/tools/xarray.py
xmca-1.4.2.post2.dist-info/LICENSE
xmca-1.4.2.post2.dist-info/METADATA
xmca-1.4.2.post2.dist-info/WHEEL
xmca-1.4.2.post2.dist-info/top_level.txt
xmca-1.4.2.post2.dist-info/RECORD
