Metadata-Version: 2.1
Name: xmca
Version: 1.4.2.post2
Summary: Maximum Covariance Analysis in Python
Home-page: https://github.com/nicrie/xmca
Author: Niclas Rieger
Author-email: niclasrieger@gmail.com
License: MIT
Keywords: eof,analysis,mca,pca
Platform: UNKNOWN
Classifier: Programming Language :: Python :: 3
Classifier: Operating System :: OS Independent
Requires-Python: >=3.6
License-File: LICENSE
Requires-Dist: numpy (>=1.19.2)
Requires-Dist: xarray (>=0.16.2)
Requires-Dist: statsmodels (>=0.12.2)
Requires-Dist: matplotlib (>=3.3.2)
Requires-Dist: cartopy (>=0.18.0)
Requires-Dist: parameterized (>=0.8.1)
Requires-Dist: netcdf4
Requires-Dist: h5netcdf
Requires-Dist: tqdm
Requires-Dist: PyYAML
